examples/mda_plot2d.py
examples/mda_plot3d.py
examples/run.py
mdapy/__init__.py
mdapy/mda.py
ihc_mdapy-0.1.0.dist-info/METADATA
ihc_mdapy-0.1.0.dist-info/WHEEL
ihc_mdapy-0.1.0.dist-info/licenses/LICENSE
ihc_mdapy-0.1.0.dist-info/RECORD
