Metadata-Version: 2.1
Name: ihc-mdapy
Version: 0.1.0
Summary: Maximum Dissimilarity Algorithm in Python
Project-URL: Repository, https://github.com/IHCantabria/mdapy
Author: Pablo Garcia
Author-email: pablofueros@gmail.com
License-Expression: MIT
License-File: LICENSE
Requires-Python: >=3.10.0
Requires-Dist: numpy>=1.26
Requires-Dist: scipy>=1.11.2
Provides-Extra: plot
Requires-Dist: matplotlib>=3.8; extra == 'plot'
Provides-Extra: test
Requires-Dist: pytest-cov>=4.1; extra == 'test'
Requires-Dist: pytest>=7.0; extra == 'test'
